{"stem":"15816","instances":[{"docId":"sfe-1905-001__1924","docUri":"sfe-1905-001__1924.html","score":1,"contexts":[{"form":"15816","weight":"1","pos":751,"context":"...schweren Fällen sah ich die darauf gelegte Suggestion[\/] <mark>15816<\/mark>wieder abbröckeln, und dann war das Kranksein oder...","fid":"d83e1022"}]},{"docId":"sfe-1905-001__1925","docUri":"sfe-1905-001__1925.html","score":1,"contexts":[{"form":"15816","weight":"1","pos":751,"context":"...schweren Fällen sah ich die darauf gelegte Suggestion[\/] <mark>15816<\/mark>wieder abbröckeln, und dann war das Kranksein oder...","fid":"d86e1067"}]}]}