{"stem":"1707","instances":[{"docId":"sfe-1920-006__1931","docUri":"sfe-1920-006__1931.html","score":1,"contexts":[{"form":"1707","weight":"1","pos":7567,"context":"...1706 und Philosophen zusammenfallen, der alles Lebende zu- <mark>1707<\/mark>sammenhält. 1708","fid":"d224e4943"}]},{"docId":"sfe-1920-006__1925","docUri":"sfe-1920-006__1925.html","score":1,"contexts":[{"form":"1707","weight":"1","pos":7948,"context":"...nicht gibt, möchten wir darum doch nicht mitmachen. <mark>1707<\/mark>","fid":"d221e4979"}]},{"docId":"sfe-1901-001__1921","docUri":"sfe-1901-001__1921.html","score":1,"contexts":[{"form":"1707","weight":"1","pos":8274,"context":"...Traumes symbolisch zu deuten ist. Die Kenntnis der Traumsymbolik <mark>1707<\/mark> wird uns immer nur die Übersetzung einzelner Bestandteile des...","fid":"d20e5339"}]},{"docId":"sfe-1905-004__1905","docUri":"sfe-1905-004__1905.html","score":1,"contexts":[{"form":"1707","weight":"1","pos":7652,"context":"...1706 Befriedigung der erogenen Zone mit der Befriedigung des <mark>1707<\/mark> Nahrungsbedürfnisses vergesellschaftet. Wer ein Kind gesättigt 1708 von...","fid":"d107e5249"}]},{"docId":"sfe-1920-006__1920_1","docUri":"sfe-1920-006__1920.1.html","score":1,"contexts":[{"form":"1707","weight":"1","pos":7600,"context":"...lebenden Materie 1706 wie das Wachstum, aus welchem <mark>1707<\/mark> sie hervorging, und das Leben ist von 1708...","fid":"d209e6129"}]},{"docId":"sfe-1901-001__1925","docUri":"sfe-1901-001__1925.html","score":1,"contexts":[{"form":"1707","weight":"1","pos":7846,"context":"...verkörpert, es werde im Theater aufgeführt, der <mark>1707<\/mark> erste Akt sei vorüber und finde rasenden Beifall....","fid":"d23e5354"}]},{"docId":"sfe-1900-001__1900","docUri":"sfe-1900-001__1900.html","score":1,"contexts":[{"form":"1707","weight":"1","pos":8551,"context":"...(p. 163): il n’y a pas des rêves <mark>1707<\/mark> absolument raisonnables et qui ne contiennent quelque incohérence,...","fid":"d11e5280"}]},{"docId":"sfe-1920-006__1920_2","docUri":"sfe-1920-006__1920.2.html","score":1,"contexts":[{"form":"1707","weight":"1","pos":8177,"context":"...einander zu bringen, die eine auf die an- <mark>1707<\/mark>dere zurückzuführen! Wir haben von jeher eine sadistische...","fid":"d212e5028"}]},{"docId":"sfe-1905-004__1915","docUri":"sfe-1905-004__1915.html","score":1,"contexts":[{"form":"1707","weight":"1","pos":7584,"context":"...Klarheit unserer Einsichten in die Vorgänge der kind- <mark>1707<\/mark>lichen Latenz- oder Aufschubsperiode zu täuschen, wollen...","fid":"d113e5404"}]},{"docId":"sfe-1901-001__1911","docUri":"sfe-1901-001__1911.html","score":1,"contexts":[{"form":"1707","weight":"1","pos":8325,"context":"...in den Witzen und im Folklore. Sie ge- <mark>1707<\/mark>stattet uns die innigen Beziehungen des Traumes zu diesen...","fid":"d17e5334"}]},{"docId":"sfe-1921-001__1925","docUri":"sfe-1921-001__1925.html","score":1,"contexts":[{"form":"1707","weight":"1","pos":7977,"context":"...Regression der seelischen Tätigkeit auf eine frühere Stufe, <mark>1707<\/mark> wie wir sie bei Wilden oder bei Kindern zu...","fid":"d230e5080"}]},{"docId":"sfe-1920-006__1921","docUri":"sfe-1920-006__1921.html","score":1,"contexts":[{"form":"1707","weight":"1","pos":7779,"context":"...näher an das psychologische Ich herantasten konnte, das ihr <mark>1707<\/mark> zunächst nur als verdrängende, zensurierende und zu Schutz...","fid":"d215e4959"}]},{"docId":"sfe-1905-004__1924","docUri":"sfe-1905-004__1924.html","score":1,"contexts":[{"form":"1707","weight":"1","pos":8073,"context":"...man eine Vermutung wagen. Die sexuellen Regungen dieser <mark>1707<\/mark> Kinderjahre wären einerseits unverwendbar, da die Fortpflanzungs-...","fid":"d122e5382"}]},{"docId":"sfe-1905-004__1910","docUri":"sfe-1905-004__1910.html","score":1,"contexts":[{"form":"1707","weight":"1","pos":7687,"context":"Autoerotismus. <mark>1707<\/mark>","fid":"d110e5472"}]},{"docId":"sfe-1923-005__1923","docUri":"sfe-1923-005__1923.html","score":1,"contexts":[{"form":"1707","weight":"1","pos":6994,"context":"...auf verschiedenen 1706 Wegen. Zunächst durch möglichst beschleunigte Nach- <mark>1707<\/mark>giebigkeit gegen die Forderungen der nicht desexuali- 1708...","fid":"d302e5086"}]},{"docId":"sfe-1920-006__1923","docUri":"sfe-1920-006__1923.html","score":1,"contexts":[{"form":"1707","weight":"1","pos":6962,"context":"...Tod fällt bei ihnen immer mit der Fort- <mark>1707<\/mark>pflanzung zusammen, aber er wird durch diese gewisser-...","fid":"d218e4904"}]},{"docId":"sfe-1901-001__1931","docUri":"sfe-1901-001__1931.html","score":1,"contexts":[{"form":"1707","weight":"1","pos":7491,"context":"...1706fluß auf die seelischen Regungen mit eifersüchtiger Strenge <mark>1707<\/mark> festhält, und die durch ihre Stellung zum Bewußtsein...","fid":"d26e5296"}]}]}