{"stem":"1793","instances":[{"docId":"sfe-1905-004__1922","docUri":"sfe-1905-004__1922.html","score":1,"contexts":[{"form":"1793","weight":"1","pos":8273,"context":"...1792erinnerungen der Neurotiker gestatten etwa folgendes Bild von <mark>1793<\/mark> dem sexuellen Verhalten der Kinderzeit zu entwerfen1):...","fid":"d113e5661"}]},{"docId":"sfe-1905-004__1905","docUri":"sfe-1905-004__1905.html","score":1,"contexts":[{"form":"1793","weight":"1","pos":8049,"context":"Infantiles 1792 Sexualziel. <mark>1793<\/mark>","fid":"d101e5494"}]},{"docId":"sfe-1901-001__1925","docUri":"sfe-1901-001__1925.html","score":1,"contexts":[{"form":"1793","weight":"1","pos":8263,"context":"...1792 Genitalien durch eine Anzahl von oft sehr überraschenden <mark>1793<\/mark> Symbolen dargestellt werden und finden sich die mannigfaltigsten 1794...","fid":"d20e5628"}]},{"docId":"sfe-1905-004__1920","docUri":"sfe-1905-004__1920.html","score":1,"contexts":[{"form":"1793","weight":"1","pos":8327,"context":"...scheint gewiß, daß das Neugeborene Keime von se- <mark>1793<\/mark>xuellen Regungen mitbringt, die sich eine Zeitlang weiter...","fid":"d110e5837"}]},{"docId":"sfe-1905-004__1915","docUri":"sfe-1905-004__1915.html","score":1,"contexts":[{"form":"1793","weight":"1","pos":7975,"context":"...hat, die es nun zu erneuern strebt. Die <mark>1793<\/mark> erste und lebenswichtigste Tätigkeit des Kindes, das Saugen...","fid":"d107e5643"}]},{"docId":"sfe-1905-004__1910","docUri":"sfe-1905-004__1910.html","score":1,"contexts":[{"form":"1793","weight":"1","pos":8078,"context":"...wie das Beispiel des Ludelns zeigt. Dasselbe Beispiel <mark>1793<\/mark> lehrt aber auch, daß jede beliebige andere Haut-...","fid":"d104e5707"}]},{"docId":"sfe-1905-004__1925","docUri":"sfe-1905-004__1925.html","score":1,"contexts":[{"form":"1793","weight":"1","pos":8739,"context":"...mitbringt, die sich eine Zeitlang weiter entwickeln, <mark>1793<\/mark> dann aber einer fortschreitenden Unterdrückung unterliegen, 1794 welche...","fid":"d119e5784"}]},{"docId":"sfe-1901-001__1931","docUri":"sfe-1901-001__1931.html","score":1,"contexts":[{"form":"1793","weight":"1","pos":7889,"context":"...drängten Wunsches einfügt, ihn so seiner Realität beraubt <mark>1793<\/mark> und wie ein Stück des psychischen Materials behandelt....","fid":"d23e5478"}]}]}