{"stem":"2060","instances":[{"docId":"sfe-1905-004__1910","docUri":"sfe-1905-004__1910.html","score":1,"contexts":[{"form":"2060","weight":"1","pos":9321,"context":"...schon in den Kinderjahren als zunächst von der erogenen <mark>2060<\/mark> Sexualtätigkeit gesonderte, selbständige Strebungen bemerkbar 2061 werden. Das...","fid":"d104e6371"}]},{"docId":"sfe-1905-004__1922","docUri":"sfe-1905-004__1922.html","score":1,"contexts":[{"form":"2060","weight":"1","pos":9491,"context":"...2059 Annahme die empfehlenswerteste sein wird. Wir werden später <mark>2060<\/mark> vielleicht auf Gründe stoßen, welche die Besonderheitsqualität 2061...","fid":"d113e6407"}]},{"docId":"sfe-1905-004__1925","docUri":"sfe-1905-004__1925.html","score":1,"contexts":[{"form":"2060","weight":"1","pos":10018,"context":"...in der Symptomatologie der Hysterie wieder. Bei dieser Neurose <mark>2060<\/mark> betrifft die Verdrängung die eigentlichen Genitalzonen am aller- 2061...","fid":"d119e6518"}]},{"docId":"sfe-1905-004__1905","docUri":"sfe-1905-004__1905.html","score":1,"contexts":[{"form":"2060","weight":"1","pos":9310,"context":"...- 2059wicklung des Schau- und Grausamkeitstriebes Beeinflussungen <mark>2060<\/mark> bestehen, welche die behauptete Unabhängigkeit der beiden 2061...","fid":"d101e6123"}]},{"docId":"sfe-1905-004__1920","docUri":"sfe-1905-004__1920.html","score":1,"contexts":[{"form":"2060","weight":"1","pos":9544,"context":"Die erogene Eigenschaft kann einzelnen Körperstellen in <mark>2060<\/mark> ausgezeichneter Weise anhaften. Es gibt prädestinierte erogene[\/]...","fid":"d110e6627"}]},{"docId":"sfe-1905-004__1915","docUri":"sfe-1905-004__1915.html","score":1,"contexts":[{"form":"2060","weight":"1","pos":9194,"context":"...können 2059 nur durch genauere Zergliederung einzelner Fälle erläutert <mark>2060<\/mark> werden. Aber alle Einzelheiten dieser zweiten infantilen 2061 Sexualbetätigung...","fid":"d107e6336"}]}]}