{"stem":"2576","instances":[{"docId":"sfe-1905-004__1924","docUri":"sfe-1905-004__1924.html","score":1,"contexts":[{"form":"2576","weight":"1","pos":12201,"context":"Muskel- <mark>2576<\/mark>tätigkeit 2577","fid":"d116e7766"}]},{"docId":"sfe-1905-004__1910","docUri":"sfe-1905-004__1910.html","score":1,"contexts":[{"form":"2576","weight":"1","pos":11744,"context":"...2575 Sexualspannung rührt, die bei der Befriedigung erogener <mark>2576<\/mark> Zonen gleichzeitig mit der Lust entsteht, und welches...","fid":"d104e7725"}]},{"docId":"sfe-1905-004__1922","docUri":"sfe-1905-004__1922.html","score":1,"contexts":[{"form":"2576","weight":"1","pos":11876,"context":"...lebens hervorgehoben, daß es wesentlich autoerotisch ist (sein <mark>2576<\/mark> Objekt am eigenen Leibe findet), und daß seine...","fid":"d113e7780"}]},{"docId":"sfe-1905-004__1925","docUri":"sfe-1905-004__1925.html","score":1,"contexts":[{"form":"2576","weight":"1","pos":12454,"context":"...Als Rest dieser fiktiven, uns durch die Pathologie <mark>2576<\/mark> aufgenötigten Organisationsphase kann das Lutschen angesehen[\/] 2577[73]werden,...","fid":"d119e7902"}]},{"docId":"sfe-1905-004__1905","docUri":"sfe-1905-004__1905.html","score":1,"contexts":[{"form":"2576","weight":"1","pos":11728,"context":"...darum nicht, weil wir nicht wissen, an welches Organ <mark>2576<\/mark> oder an welche Organe die Geschlechtlichkeit gebunden ist, seit-...","fid":"d101e7458"}]},{"docId":"sfe-1905-004__1920","docUri":"sfe-1905-004__1920.html","score":1,"contexts":[{"form":"2576","weight":"1","pos":11923,"context":"...am eigenen Leibe findet), und daß seine einzelnen <mark>2576<\/mark> Partialtriebe im ganzen unverknüpft und unabhängig von ein- 2577...","fid":"d110e8011"}]},{"docId":"sfe-1905-004__1915","docUri":"sfe-1905-004__1915.html","score":1,"contexts":[{"form":"2576","weight":"1","pos":11547,"context":"Affekt- <mark>2576<\/mark>vorgänge. 2577","fid":"d107e7747"}]}]}