{"stem":"283","instances":[{"docId":"sfe-1905-004__1922","docUri":"sfe-1905-004__1922.html","score":2,"contexts":[{"form":"283","weight":"1","pos":1287,"context":"...aber allen Grund, in diesen Angaben ein sehr <mark>283<\/mark> ungetreues Abbild der Wirklichkeit zu erblicken; faßt man...","fid":"d119e1359"},{"form":"283","weight":"1","pos":11582,"context":"...§ 279 § 280 § 281 § 282 § <mark>283<\/mark> § 284 § 285 § 286 1) Man hat...","fid":"page"}]},{"docId":"sfe-1905-004__1905","docUri":"sfe-1905-004__1905.html","score":2,"contexts":[{"form":"283","weight":"1","pos":1143,"context":"...haut der Nase, des Kachens, des Kehlkopfos <mark>283<\/mark> und der Luftröhre, 1802, M. 4.—, 284...","fid":"d107e1320"},{"form":"283","weight":"1","pos":6849,"context":"...§ 279 § 280 § 281 § 282 § <mark>283<\/mark> § 284 § 285§ 286 *) Letzteres Material...","fid":"page"}]},{"docId":"sfe-1905-004__1920","docUri":"sfe-1905-004__1920.html","score":2,"contexts":[{"form":"283","weight":"1","pos":1346,"context":"...Abbild der Wirklichkeit zu erblicken; faßt man sie <mark>283<\/mark> schärfer ins Auge, so erweisen sie sich überreich...","fid":"d116e1364"},{"form":"283","weight":"1","pos":11628,"context":"...§ 279 § 280 § 281 § 282 § <mark>283<\/mark> § 284 § 285 ) Man hat das Recht,...","fid":"page"}]},{"docId":"sfe-1900-001__1900","docUri":"sfe-1900-001__1900.html","score":2,"contexts":[{"form":"283","weight":"1","pos":1375,"context":"...Feld, sah eine fünfte, eine sechste Eidechse den <mark>283<\/mark> Weg zu dem Loch in der Mauer nehmen,...","fid":"d11e1110"},{"form":"283","weight":"1","pos":17595,"context":"...§ 279 § 280 § 281 § 282 § <mark>283<\/mark> § 284 § 285 79 § 286 § 287...","fid":"page"}]},{"docId":"sfe-1921-001__1925","docUri":"sfe-1921-001__1925.html","score":2,"contexts":[{"form":"283","weight":"1","pos":1322,"context":"...Zug darin, dessen Ableitung und Unterbringung dem Psycho- <mark>283<\/mark>analytiker Schwierigkeiten bereiten würde. Le Bon weist uns 284...","fid":"d230e1168"},{"form":"283","weight":"1","pos":3208,"context":"...den seelischen Vorgängen im Individuum bedeutete. 686 [<mark>283<\/mark>] § 72§ 73 § 74 § 75...","fid":"page"}]},{"docId":"sfe-1905-004__1910","docUri":"sfe-1905-004__1910.html","score":2,"contexts":[{"form":"283","weight":"1","pos":1167,"context":"...sind zwei Angaben enthalten, die unabhängig von ein- <mark>283<\/mark>ander beurteilt werden sollen: Das Angeborensein und die 284...","fid":"d110e1440"},{"form":"283","weight":"1","pos":9898,"context":"...Entwicklung des kindlichen Denkvermögens. 2179 § 282 § <mark>283<\/mark> 1) Manche Personen wissen sich zu erinnern, daß...","fid":"page"}]},{"docId":"sfe-1905-004__1925","docUri":"sfe-1905-004__1925.html","score":2,"contexts":[{"form":"283","weight":"1","pos":1523,"context":"..., dem Hunger. Eine dem Worte „Hunger“ <mark>283<\/mark> entsprechende Bezeichnung fehlt der Volkssprache; die Wissenschaft 284...","fid":"d125e1360"},{"form":"283","weight":"1","pos":10264,"context":"...nicht gesichert ist. 2104 § 281§ 282 § <mark>283<\/mark> § 284 1) Vgl. hiezu die sehr reichhaltige...","fid":"page"}]},{"docId":"sfe-1904-002__1904","docUri":"sfe-1904-002__1904.html","score":1,"contexts":[{"form":"283","weight":"1","pos":1401,"context":"...verursachte oder im Bereiche einzelner Neurosen vorkommende Zwangs- <mark>283<\/mark>erscheinungen zugänglich. Sie kann, wie wir schon erwähnten...","fid":"d38e1350"}]},{"docId":"sfe-1905-001__1906","docUri":"sfe-1905-001__1906.html","score":1,"contexts":[{"form":"283","weight":"1","pos":1276,"context":"...sich nicht selbst durch ihre Leiden zur Therapie gedrängt <mark>283<\/mark> fühlen, sondern sich einer solchen nur infolge des...","fid":"d77e1388"}]},{"docId":"sfe-1905-001__1920","docUri":"sfe-1905-001__1920.html","score":1,"contexts":[{"form":"283","weight":"1","pos":1302,"context":".... Ich halte es für durchaus nicht ausgeschlossen, <mark>283<\/mark> daß man bei geeigneter Abänderung des Verfahrens sich über...","fid":"d83e1408"}]},{"docId":"sfe-1901-001__1901","docUri":"sfe-1901-001__1901.html","score":1,"contexts":[{"form":"283","weight":"1","pos":1248,"context":"...werde hier Halt machen, um die bisherigen Ergebnisse der <mark>283<\/mark> Traumanalyse zu überblicken. Indem ich den Associationen folgte...","fid":"d14e1348"}]},{"docId":"sfe-1920-006__1931","docUri":"sfe-1920-006__1931.html","score":1,"contexts":[{"form":"283","weight":"1","pos":1275,"context":"...jede fremde Beihilfe gepflegt und betreut hatte. Dieses brave <mark>283<\/mark> Kind zeigte nun die gelegentlich störende Gewohnheit, alle...","fid":"d224e1212"}]},{"docId":"sfe-1905-001__1925","docUri":"sfe-1905-001__1925.html","score":1,"contexts":[{"form":"283","weight":"1","pos":1314,"context":"...man bei geeigneter Abänderung des Verfahrens sich über diese <mark>283<\/mark> Gegenindikation hinaussetzen und so eine Psychotherapie der 284 Psychosen...","fid":"d92e1467"}]},{"docId":"sfe-1905-001","docUri":"sfe-1905-001.html","score":1,"contexts":[{"form":"283","weight":"1","pos":1402,"context":"...bringen kann. Wo aber mit der analytischen Psychotherapie nur <mark>283<\/mark> wenig auszurichten war, da, darf man getrost behaupten,...","fid":"d15e1782"}]},{"docId":"sfe-1920-006__1925","docUri":"sfe-1920-006__1925.html","score":1,"contexts":[{"form":"283","weight":"1","pos":1330,"context":"...hatte. Dieses brave Kind zeigte nun die gelegentlich störende <mark>283<\/mark> Gewohnheit, alle kleinen Gegenstände, deren es habhaft...","fid":"d221e1226"}]},{"docId":"sfe-1920-001__1924","docUri":"sfe-1920-001__1924.html","score":1,"contexts":[{"form":"283","weight":"1","pos":1317,"context":"...282 anderer Fragen ungeduldig erwarten. Zeigte dieses homosexuelle <mark>283<\/mark> Mädchen deutliche somatische Charaktere des anderen Geschlechts 284 und...","fid":"d167e1130"}]},{"docId":"sfe-1905-001__1911","docUri":"sfe-1905-001__1911.html","score":1,"contexts":[{"form":"283","weight":"1","pos":1302,"context":".... Ich halte es für durchaus nicht ausgeschlossen, <mark>283<\/mark> daß man bei geeigneter Abänderung des Verfahrens sich über...","fid":"d80e1403"}]},{"docId":"sfe-1901-001__1921","docUri":"sfe-1901-001__1921.html","score":1,"contexts":[{"form":"283","weight":"1","pos":1325,"context":"...ich diese Schwierigkeit vermeiden, wenn ich den Traum <mark>283<\/mark> eines Anderen zur Analyse brächte, es sei denn,...","fid":"d20e1261"}]},{"docId":"sfe-1920-006__1919","docUri":"sfe-1920-006__1919.html","score":1,"contexts":[{"form":"283","weight":"1","pos":1162,"context":"...ergiebt keine 282 sichere Entscheidung. Bei unbefangener Betrachtung <mark>283<\/mark> gewinnt man den Eindruck, daß das Kind das...","fid":"d206e1360"}]},{"docId":"sfe-1905-002__1937","docUri":"sfe-1905-002__1937.html","score":1,"contexts":[{"form":"283","weight":"1","pos":1529,"context":"...geworden ist, weit mehr, als sie anderen Ärzten leisten <mark>283<\/mark> können. So gibt es menschliche Wundertäter ebenso wie göttliche...","fid":"d104e1204"}]},{"docId":"sfe-1920-006__1920_1","docUri":"sfe-1920-006__1920.1.html","score":1,"contexts":[{"form":"283","weight":"1","pos":1291,"context":"...ihn zu denken. Wenn man es als selbst- <mark>283<\/mark>verständlich hinnimmt, dass der nächtliche Traum sie wieder...","fid":"d209e1417"}]},{"docId":"sfe-1901-001__1925","docUri":"sfe-1901-001__1925.html","score":1,"contexts":[{"form":"283","weight":"1","pos":1322,"context":"...282 Beispiel die Gegensätze von eigennützig—uneigennützig, <mark>283<\/mark> die Elemente schuldig sein und umsonst tun. Ich könnte...","fid":"d23e1298"}]},{"docId":"sfe-1905-001__1922","docUri":"sfe-1905-001__1922.html","score":1,"contexts":[{"form":"283","weight":"1","pos":1302,"context":".... Ich halte es für durchaus nicht ausgeschlossen, <mark>283<\/mark> daß man bei geeigneter Abänderung des Verfahrens sich über...","fid":"d86e1409"}]},{"docId":"sfe-1923-003__1925","docUri":"sfe-1923-003__1925.html","score":1,"contexts":[{"form":"283","weight":"1","pos":1273,"context":"...nicht zu erweisen, denn die beiden Situationen sind <mark>283<\/mark> nicht vergleichbar; die Verwertung in der Analyse ist...","fid":"d284e1221"}]},{"docId":"sfe-1905-002__1905","docUri":"sfe-1905-002__1905.html","score":1,"contexts":[{"form":"283","weight":"1","pos":1484,"context":"...seelischen Triebkräfte darstellen. Solche Modekuren entfalten Heil- <mark>283<\/mark>wirkungen, die nicht in ihrem Machtbereich gelegen sind,...","fid":"d98e1185"}]},{"docId":"sfe-1922-002__1922","docUri":"sfe-1922-002__1922.html","score":1,"contexts":[{"form":"283","weight":"1","pos":1358,"context":"...genommen, was im Wachleben derzeit zurückgedrängt war. Aber <mark>283<\/mark> auch das braucht nicht die Regel zu sein. 284...","fid":"d254e1067"}]},{"docId":"sfe-1901-001","docUri":"sfe-1901-001.html","score":1,"contexts":[{"form":"283","weight":"1","pos":1526,"context":"...stück zu dieser Arbeit, welches die entgegengesetzte Umwandlung <mark>283<\/mark> leistet, kenne ich bereits als Analysenarbeit. Die...","fid":"d11e2877"}]},{"docId":"sfe-1905-001__1905_2","docUri":"sfe-1905-001__1905.2.html","score":1,"contexts":[{"form":"283","weight":"1","pos":1213,"context":"...und durch Jahre in Anstalten geweilt hatten. Ich habe <mark>283<\/mark> kaum Erfahrung genug gesammelt, um Ihnen sagen zu...","fid":"d71e1386"}]},{"docId":"sfe-1905-002__1918","docUri":"sfe-1905-002__1918.html","score":1,"contexts":[{"form":"283","weight":"1","pos":1484,"context":"...seelischen Triebkräfte darstellen. Solche Modekuren entfalten Heil- <mark>283<\/mark>wirkungen, die nicht in ihrem Machtbereich gelegen sind,...","fid":"d101e1185"}]},{"docId":"sfe-1923-002__1928","docUri":"sfe-1923-002__1928.html","score":1,"contexts":[{"form":"283","weight":"1","pos":1538,"context":"...gutes zu sein. Die Symbolgemeinschaft reicht über die Sprachgemeinschaft <mark>283<\/mark> hinaus. 284","fid":"d278e1204"}]},{"docId":"sfe-1922-002__1922_2","docUri":"sfe-1922-002__1922.2.html","score":1,"contexts":[{"form":"283","weight":"1","pos":1353,"context":".... Der Traum hat also in beiden Fällen auf- <mark>283<\/mark>genommen, was im Wachleben derzeit zurückgedrängt war. Aber...","fid":"d251e1065"}]},{"docId":"sfe-1923-004__1924","docUri":"sfe-1923-004__1924.html","score":1,"contexts":[{"form":"283","weight":"1","pos":1334,"context":"...Erkrankung war, die der Maler selbst in den Bemerkungen <mark>283<\/mark> zu den Teufelsbildern geradezu eine Melancholie nennt („solte...","fid":"d296e1277"}]},{"docId":"sfe-1923-005__1925","docUri":"sfe-1923-005__1925.html","score":1,"contexts":[{"form":"283","weight":"1","pos":1234,"context":"...waren 282 einmal Wahrnehmungen und können wie alle Erinnerungsreste <mark>283<\/mark> wieder bewußt werden. Ehe wir noch weiter von ihrer...","fid":"d305e1237"}]},{"docId":"sfe-1923-002__1926","docUri":"sfe-1923-002__1926.html","score":1,"contexts":[{"form":"283","weight":"1","pos":1219,"context":"...282 aus der Deutung der Träume her. Die Psychoanalyse <mark>283<\/mark> hat dem Traum die Bedeutung wiedergegeben, die ihm...","fid":"d275e1137"}]},{"docId":"sfe-1905-001__1905","docUri":"sfe-1905-001__1905.html","score":1,"contexts":[{"form":"283","weight":"1","pos":1267,"context":"...sie existenzunfähig macht, auf die Krankheit zu schieben, <mark>283<\/mark> wenn sie irgend einen Anflug von Neurose zeigen....","fid":"d74e1378"}]},{"docId":"sfe-1905-002__1905_2","docUri":"sfe-1905-002__1905.2.html","score":1,"contexts":[{"form":"283","weight":"1","pos":1475,"context":".... Das Ansehen und die Massenwirkung ersetzen ihnen vollauf <mark>283<\/mark> den religiösen Glauben. Es gibt jederzeit Modekuren und...","fid":"d95e1209"}]},{"docId":"sfe-1920-006__1920_2","docUri":"sfe-1920-006__1920.2.html","score":1,"contexts":[{"form":"283","weight":"1","pos":1281,"context":"...einanderhalten. Angst bezeichnet einen gewissen Zustand wie Er- <mark>283<\/mark>wartung der Gefahr und Vorbereitung auf dieselbe, mag sie...","fid":"d212e1258"}]},{"docId":"sfe-1923-003__1923_1","docUri":"sfe-1923-003__1923.1.html","score":1,"contexts":[{"form":"283","weight":"1","pos":1285,"context":"...geben, eine unbewußte Macht, welche während.des Schlaf- <mark>283<\/mark>zustandes besser als sonst imstande ist, die Absichten der...","fid":"d281e1180"}]},{"docId":"sfe-1920-001__1920","docUri":"sfe-1920-001__1920.html","score":1,"contexts":[{"form":"283","weight":"1","pos":1376,"context":"...- 282phroditismus von dem des psychischen im hohen <mark>283<\/mark> Grade unabhängig ist. Als Einschränkung der beiden Sätze 284...","fid":"d161e1114"}]},{"docId":"sfe-1905-004__1915","docUri":"sfe-1905-004__1915.html","score":1,"contexts":[{"form":"283","weight":"1","pos":11932,"context":"...279 67 § 280 § 281 § 282 § <mark>283<\/mark> § 284 § 285 68 § 286 § 287...","fid":"page"}]},{"docId":"sfe-1901-001__1911","docUri":"sfe-1901-001__1911.html","score":1,"contexts":[{"form":"283","weight":"1","pos":1314,"context":"...Die Antwort lautet, weil jeder Traum, mit <mark>283<\/mark> dem ich mich beschäftigen will, zu denselben schwer mitteilbaren...","fid":"d17e1260"}]},{"docId":"sfe-1923-003__1931","docUri":"sfe-1923-003__1931.html","score":1,"contexts":[{"form":"283","weight":"1","pos":1223,"context":".... lch mußte antworten, mit sei von einem <mark>283<\/mark> solchen Mechanismus der Traumbildung noch nichts bekannt 284 werden,...","fid":"d287e1186"}]},{"docId":"sfe-1923-004__1924_2","docUri":"sfe-1923-004__1924.2.html","score":1,"contexts":[{"form":"283","weight":"1","pos":1364,"context":"...Bericht des Abtes Franciscus weiß auch die Quelle dieser <mark>283<\/mark> Verzagtheit oder Verstimmung zu nennen, denn hier heißt...","fid":"d293e1244"}]},{"docId":"sfe-1922-001__1922_2","docUri":"sfe-1922-001__1922.2.html","score":1,"contexts":[{"form":"283","weight":"1","pos":1402,"context":"...Anfang seines zweiten Briefes sagt, bei einer mündlichen Aus- <mark>283<\/mark>sprache wäre mehr herausgekommen. 284","fid":"d248e960"}]},{"docId":"sfe-1920-006__1921","docUri":"sfe-1920-006__1921.html","score":1,"contexts":[{"form":"283","weight":"1","pos":1228,"context":"...sei wie so vieles andere auch die Traum- <mark>283<\/mark>funktion erschüttert und von ihren Absichten abgelenkt wor-...","fid":"d215e1244"}]},{"docId":"sfe-1905-004__1924","docUri":"sfe-1905-004__1924.html","score":1,"contexts":[{"form":"283","weight":"1","pos":13128,"context":"...§ 279 § 280 § 281§ 282 § <mark>283<\/mark> § 284 § 285 § 286 § 287 §...","fid":"page"}]},{"docId":"sfe-1905-001__1924","docUri":"sfe-1905-001__1924.html","score":1,"contexts":[{"form":"283","weight":"1","pos":1314,"context":"...man bei geeigneter Abänderung des Verfahrens sich über diese <mark>283<\/mark> Gegenindikation hinaussetzen und so eine Psychotherapie der 284 Psychosen...","fid":"d89e1422"}]},{"docId":"sfe-1923-005__1923","docUri":"sfe-1923-005__1923.html","score":1,"contexts":[{"form":"283","weight":"1","pos":1194,"context":"...seheit-Verrir tes ist von Erzilllern unserer Sprache <mark>283<\/mark> noch nicht gewagt werden. Man muß zu den Großen...","fid":"d302e1183"}]},{"docId":"sfe-1920-006__1923","docUri":"sfe-1920-006__1923.html","score":1,"contexts":[{"form":"283","weight":"1","pos":1095,"context":"...seelischen 282 Tiefenvorgänge betrachten. Nun zeigt das Traumleben <mark>283<\/mark> der traumatischen Neurose den Charakter, daß es den...","fid":"d218e1283"}]},{"docId":"sfe-1920-001__1922","docUri":"sfe-1920-001__1922.html","score":1,"contexts":[{"form":"283","weight":"1","pos":1270,"context":"...und hatte sich bis zum Selbstmordversuch immer nur streng <mark>283<\/mark> abweisend gegen sie benommen. 284","fid":"d164e1097"}]},{"docId":"sfe-1901-001__1931","docUri":"sfe-1901-001__1931.html","score":1,"contexts":[{"form":"283","weight":"1","pos":1243,"context":"...282denen Ketten zusammen, in denen gewisse Vorstellungen als <mark>283<\/mark> zentrale wiederholt vorkommen. Solche im Traum selbst nicht...","fid":"d26e1252"}]},{"docId":"sfe-1923-004__1928","docUri":"sfe-1923-004__1928.html","score":1,"contexts":[{"form":"283","weight":"1","pos":1207,"context":".... Diese[\/] 28228Leistungen oder Verpflichtungen des Teufels pflegen <mark>283<\/mark> auch im Vertrag mit ihm ausdrücklich erwähnt zu 284...","fid":"d299e1293"}]},{"docId":"sfe-1923-002__1923","docUri":"sfe-1923-002__1923.html","score":1,"contexts":[{"form":"283","weight":"1","pos":1227,"context":"...zum größten Teil dem Träumer selbst, indem sie ihn <mark>283<\/mark> nach seinen Assoziationen zu den einzelnen Elementen 284 des...","fid":"d272e1136"}]}]}