{"stem":"3256","instances":[{"docId":"sfe-1905-004__1922","docUri":"sfe-1905-004__1922.html","score":1,"contexts":[{"form":"3256","weight":"1","pos":15068,"context":"...3255 In der Sonderung von libidinöser und anderer psychischer <mark>3256<\/mark> Energie drücken wir die Voraussetzung aus, daß sich die...","fid":"d113e9549"}]},{"docId":"sfe-1905-004__1920","docUri":"sfe-1905-004__1920.html","score":1,"contexts":[{"form":"3256","weight":"1","pos":15108,"context":"...Energie drücken wir die Voraussetzung aus, daß sich die <mark>3256<\/mark> Sexualvorgänge des Organismus durch einen besonderen Chemis- 3257...","fid":"d110e9806"}]},{"docId":"sfe-1905-004__1915","docUri":"sfe-1905-004__1915.html","score":1,"contexts":[{"form":"3256","weight":"1","pos":14624,"context":"...übrig, welches die Objektwahl vorbereiten, das verlorene <mark>3256<\/mark> Glück also wiederherstellen hilft. Die ganze Latenzzeit über...","fid":"d107e9488"}]},{"docId":"sfe-1905-004__1924","docUri":"sfe-1905-004__1924.html","score":1,"contexts":[{"form":"3256","weight":"1","pos":15433,"context":"...es nur später, vielleicht gerade zur Zeit, als es <mark>3256<\/mark> dem Kinde möglich wurde, die Gesamtvorstellung der Person,...","fid":"d116e9538"}]},{"docId":"sfe-1905-004__1910","docUri":"sfe-1905-004__1910.html","score":1,"contexts":[{"form":"3256","weight":"1","pos":14913,"context":"...dieser Form scheint mir die Aufstellung unhaltbar; sie <mark>3256<\/mark> wird aber sinnreich, wenn eine konstitutionelle Schwäche 3257...","fid":"d104e9355"}]},{"docId":"sfe-1905-004__1925","docUri":"sfe-1905-004__1925.html","score":1,"contexts":[{"form":"3256","weight":"1","pos":15704,"context":"...3255 führt. Die Psychoanalyse der sogenannten Übertragungsneurosen[\/] <mark>3256<\/mark>[93](Hysterie und Zwangsneurose) gestattet uns hier einen...","fid":"d119e9731"}]}]}