{"stem":"3648","instances":[{"docId":"sfe-1905-004__1924","docUri":"sfe-1905-004__1924.html","score":1,"contexts":[{"form":"3648","weight":"1","pos":17313,"context":"...Weise mit der Befriedigung von anderen Quellen her gleich- <mark>3648<\/mark>zeitig eine Sexualerregung erzeugt werde, die zu der Genitalzone...","fid":"d116e10579"}]},{"docId":"sfe-1905-004__1922","docUri":"sfe-1905-004__1922.html","score":1,"contexts":[{"form":"3648","weight":"1","pos":16856,"context":"...die infantil bevorzugten Personen mit Sicherheit 3647 aufdecken. <mark>3648<\/mark>","fid":"d113e10561"}]},{"docId":"sfe-1905-004__1925","docUri":"sfe-1905-004__1925.html","score":1,"contexts":[{"form":"3648","weight":"1","pos":17554,"context":"...geht wohl die Objektwahl überhaupt vor sich. Vor allem <mark>3648<\/mark> sucht der Mann nach dem Erinnerungsbild der Mutter,...","fid":"d119e10784"}]},{"docId":"sfe-1905-004__1920","docUri":"sfe-1905-004__1920.html","score":1,"contexts":[{"form":"3648","weight":"1","pos":16889,"context":"...3647 Libido auf die infantil bevorzugten Personen mit Sicherheit <mark>3648<\/mark> aufdecken. 3649","fid":"d110e10858"}]},{"docId":"sfe-1905-004__1915","docUri":"sfe-1905-004__1915.html","score":1,"contexts":[{"form":"3648","weight":"1","pos":16434,"context":"...und fanden, daß zum Weibwerden eine neuer- <mark>3648<\/mark>liche Verdrängung erforderlich ist, welche ein Stück infantiler 3649...","fid":"d107e10452"}]}]}