{"stem":"3843","instances":[{"docId":"sfe-1905-004__1922","docUri":"sfe-1905-004__1922.html","score":1,"contexts":[{"form":"3843","weight":"1","pos":17793,"context":"Welches Maß von sexuellen Betätigungen im Kindesalter <mark>3843<\/mark> noch als normal, der weiteren Entwicklung nicht abträglich...","fid":"d113e11112"}]},{"docId":"sfe-1905-004__1920","docUri":"sfe-1905-004__1920.html","score":1,"contexts":[{"form":"3843","weight":"1","pos":17822,"context":"...man in der Urgeschichte 3842 der Menschenart suchen. <mark>3843<\/mark>","fid":"d110e11395"}]},{"docId":"sfe-1905-004__1924","docUri":"sfe-1905-004__1924.html","score":1,"contexts":[{"form":"3843","weight":"1","pos":18216,"context":"...psychischen 3842 Leistungsfähigkeit aus der an sich gefährlichen Veranlagung <mark>3843<\/mark> resultiert. Eine der Quellen der Kunstbetätigung ist hier...","fid":"d116e11079"}]},{"docId":"sfe-1905-004__1925","docUri":"sfe-1905-004__1925.html","score":1,"contexts":[{"form":"3843","weight":"1","pos":18490,"context":"...nicht nachweisbar. Die Ableitung der Herkunft dieser mensch- <mark>3843<\/mark>lichen Eigenschaft müßte man in der Urgeschichte der Menschenart...","fid":"d119e11305"}]}]}