{"stem":"abkömml","instances":[{"docId":"sfe-1900-001__1900","docUri":"sfe-1900-001__1900.html","score":4,"contexts":[{"form":"Abkömmling","weight":"1","pos":49904,"context":"...Traumes kann man oft einzig und allein einen directen <mark>Abkömmling<\/mark> 10069 dessen entdecken, was in den Traumgedanken übermässig...","fid":"d11e28943"},{"form":"Abkömmling","weight":"1","pos":66700,"context":"...Traumes oder einzelner Traumdaten ist 13529 wieder nur ein <mark>Abkömmling<\/mark> der Traumcensur, des Widerstandes 13530 gegen das Durchdringen...","fid":"d11e38675"},{"form":"Abkömmling","weight":"1","pos":66764,"context":"...wir dem 13542 Fingerzeige folgend in diesem einen directeren <mark>Abkömmling<\/mark> eines 13543 der vervehmten Traumgedanken erkennen. Es ist...","fid":"d11e38675"},{"form":"Abkömmling","weight":"1","pos":66873,"context":"...störende Wirkung des Zweifels lässt ihn als einen 13565 <mark>Abkömmling<\/mark> und als ein Werkzeug des psychischen Widerstandes 13566 entlarven...","fid":"d11e38751"}]},{"docId":"sfe-1920-006__1925","docUri":"sfe-1920-006__1925.html","score":2,"contexts":[{"form":"Abkömmling","weight":"1","pos":3241,"context":"...und die graue 699 Hirnrinde ist noch immer ein <mark>Abkömmling<\/mark> der primitiven Ober- 700ﬂäche und könnte wesentliche...","fid":"d221e2360"},{"form":"Abkömmling","weight":"1","pos":6893,"context":"...und in frisches Wasser brachte. Dieser späte 1479 <mark>Abkömmling<\/mark> des ersten Pantoffeltierchen war ebenso frisch wie[\/] 1480239der...","fid":"d221e4394"}]},{"docId":"sfe-1920-006__1920_2","docUri":"sfe-1920-006__1920.2.html","score":2,"contexts":[{"form":"Abkömmling","weight":"1","pos":3497,"context":"...und die graue Hirnrinde ist noch immer 748 ein <mark>Abkömmling<\/mark> der primitiven Oberfläche und könnte wesentliche 749 Eigenschaften derselben...","fid":"d212e2529"},{"form":"Abkömmling","weight":"1","pos":7142,"context":"...und 1490 in frisches Wasser brachte. Dieser späte <mark>Abkömmling<\/mark> des ersten 1491 Pantoffeltierchens war ebenso frisch wie der...","fid":"d212e4441"}]},{"docId":"sfe-1921-001__1925","docUri":"sfe-1921-001__1925.html","score":2,"contexts":[{"form":"Abkömmling","weight":"1","pos":6018,"context":"...Beseitigung wenden. Sie benimmt sich wie ein 1280 <mark>Abkömmling<\/mark> der ersten oralen Phase der Libidoorganisation, in 1281...","fid":"d230e3963"},{"form":"Abkömmling","weight":"1","pos":8303,"context":"...dieses Satzes, also daß die Suggestibilität ein[\/] 1776320<mark>Abkömmling<\/mark> des Herdeninstinkts sei, erschiene mir bei weitem 1777 einleuchtender...","fid":"d230e5288"}]},{"docId":"sfe-1920-006__1921","docUri":"sfe-1920-006__1921.html","score":2,"contexts":[{"form":"Abkömmling","weight":"1","pos":3309,"context":"...und die 741 graue Hirnrinde ist noch immer ein <mark>Abkömmling<\/mark> der primitiven 742 Oberfläche und könnte wesentliche Eigenschaften derselben...","fid":"d215e2448"},{"form":"Abkömmling","weight":"1","pos":7036,"context":"...und in frisches Wasser brachte. Dieser 1544 späte <mark>Abkömmling<\/mark> des ersten Pantoffeltierchens war ebenso 1545 frisch wie der...","fid":"d215e4499"}]},{"docId":"sfe-1920-006__1923","docUri":"sfe-1920-006__1923.html","score":2,"contexts":[{"form":"Abkömmling","weight":"1","pos":3308,"context":"...und die graue 826 Hirnrinde ist noch immer ein <mark>Abkömmling<\/mark> der primitiven 827 Oberfläche und könnte wesentliche Eigenschaften der...","fid":"d218e2680"},{"form":"Abkömmling","weight":"1","pos":7024,"context":"...und in frisches Wasser 1721 brachte. Dieser späte <mark>Abkömmling<\/mark> des ersten Pantoffel- 1722tierchens war ebenso frisch...","fid":"d218e4957"}]},{"docId":"sfe-1920-006__1931","docUri":"sfe-1920-006__1931.html","score":1,"contexts":[{"form":"Abkömmling","weight":"1","pos":6960,"context":"...und in frisches 1569 Wasser brachte. Dieser späte <mark>Abkömmling<\/mark> des ersten Pan- 1570toffeltierchens war ebenso frisch...","fid":"d224e4597"}]},{"docId":"sfe-1901-001__1921","docUri":"sfe-1901-001__1921.html","score":1,"contexts":[{"form":"Abkömmling","weight":"1","pos":3505,"context":"...undeutlichen Traumelement kann ich aber 725 oft den direktesten <mark>Abkömmling<\/mark> des wesentlichen Traumgedankens 726 erkennen. 727","fid":"d20e2500"}]},{"docId":"sfe-1920-006__1920_1","docUri":"sfe-1920-006__1920.1.html","score":1,"contexts":[{"form":"Abkömmling","weight":"1","pos":3510,"context":"...graue Hirn- 762rinde ist noch immer ein <mark>Abkömmling<\/mark> der primitiven Oberflä- 763che und könnte wesentliche...","fid":"d209e3144"}]},{"docId":"sfe-1901-001__1925","docUri":"sfe-1901-001__1925.html","score":1,"contexts":[{"form":"Abkömmling","weight":"1","pos":3614,"context":"...undeutlichen Traumelement kann ich aber oft den direktesten 784 <mark>Abkömmling<\/mark> des wesentlichen Traumgedankens erkennen. 785","fid":"d23e2679"}]},{"docId":"sfe-1901-001","docUri":"sfe-1901-001.html","score":1,"contexts":[{"form":"Abkömmling","weight":"1","pos":3584,"context":"...undeutlichen Traumelement kann ich aber oft den direktesten 701 <mark>Abkömmling<\/mark> des wesentlichenoi Traumgedankens erkennen.","fid":"d11e6274"}]},{"docId":"sfe-1923-005__1923","docUri":"sfe-1923-005__1923.html","score":1,"contexts":[{"form":"Abkömmling","weight":"1","pos":2412,"context":"...Bemerkte und nicht Bemerkte ist also doch nur ein <mark>Abkömmling<\/mark> des Vorurteils, dem die Identität des Psychischen mit...","fid":"page"}]},{"docId":"sfe-1901-001__1931","docUri":"sfe-1901-001__1931.html","score":1,"contexts":[{"form":"Abkömmling","weight":"1","pos":3589,"context":"...undeutlichen Traumelement kann ich aber oft den[\/] 808271direktesten <mark>Abkömmling<\/mark> des wesentlichen Traumgedankens 809 erkennen. 810","fid":"d26e2649"}]}]}