{"stem":"ausführlich","instances":[{"docId":"sfe-1901-001__1901","docUri":"sfe-1901-001__1901.html","score":2,"contexts":[{"form":"ausführlich","weight":"1","pos":722,"context":"...die sich aus seinem regelmässigen 169 Gelingen ableiten, <mark>ausführlich<\/mark> zu behandeln. Es mag also die Aussage 170...","fid":"d11e997"},{"form":"ausführlich","weight":"1","pos":5246,"context":"...von diesem Stück der Traum- 1087arbeit nicht <mark>ausführlich<\/mark> handeln, will also nur anführen, dass man...","fid":"d11e3638"}]},{"docId":"sfe-1901-001__1911","docUri":"sfe-1901-001__1911.html","score":2,"contexts":[{"form":"ausführlich","weight":"1","pos":654,"context":"...die sich aus seinem regelmäßigen 143 Gelingen ableiten, <mark>ausführlich<\/mark> zu behandeln. Es mag also die Aussage 144...","fid":"d14e906"},{"form":"ausführlich","weight":"1","pos":5203,"context":"...von diesem Stück der Traum- 1070arbeit nicht <mark>ausführlich<\/mark> handeln, will also nur anführen, dass man...","fid":"d14e3603"}]},{"docId":"sfe-1901-001__1921","docUri":"sfe-1901-001__1921.html","score":2,"contexts":[{"form":"ausführlich","weight":"1","pos":653,"context":"...die sich aus seinem regelmäßigen 140 Gelingen ableiten, <mark>ausführlich<\/mark> zu behandeln. Es mag also die Aussage 141...","fid":"d17e903"},{"form":"ausführlich","weight":"1","pos":5215,"context":"...von diesem Stück der Traum- 1076arbeit nicht <mark>ausführlich<\/mark> handeln, will also nur anführen, dass man...","fid":"d17e3618"}]},{"docId":"sfe-1901-001","docUri":"sfe-1901-001.html","score":2,"contexts":[{"form":"ausführlich","weight":"1","pos":685,"context":"...seinem regel-[\/] 119194mäßigenbl Gelingen ableiten, <mark>ausführlich<\/mark> zu behandeln. Es mag also 120 die Aussage...","fid":"d11e1575"},{"form":"ausführlich","weight":"1","pos":5287,"context":"...Ich 1025 werde von diesem Stück der Traumarbeit nicht <mark>ausführlich<\/mark> 1026 handeln, will also nur anführen, daß...","fid":"d11e9142"}]},{"docId":"sfe-1901-001__1925","docUri":"sfe-1901-001__1925.html","score":2,"contexts":[{"form":"ausführlich","weight":"1","pos":711,"context":"...aus seinem regel-[\/] 145194mäßigen Gelingen ableiten, <mark>ausführlich<\/mark> zu behandeln. Es mag also 146 die Aussage...","fid":"d20e914"},{"form":"ausführlich","weight":"1","pos":5354,"context":"...Ich 1161 werde von diesem Stück der Traumarbeit nicht <mark>ausführlich<\/mark> 1162 handeln, will also nur anführen, daß...","fid":"d20e3894"}]},{"docId":"sfe-1905-004__1925","docUri":"sfe-1905-004__1925.html","score":1,"contexts":[{"form":"ausführliche","weight":"1","pos":6517,"context":"...deren Ergebnisse im einzelnen ich an 1331 anderen Orten <mark>ausführliche<\/mark> Rechenschaft gegeben habe und noch 1332 weiter geben werde....","fid":"d119e4430"}]},{"docId":"sfe-1905-004__1910","docUri":"sfe-1905-004__1910.html","score":1,"contexts":[{"form":"ausführliche","weight":"1","pos":5013,"context":"...über deren Ergebnisse im einzelnen ich hoffe 1135 später <mark>ausführliche<\/mark> Rechenschaft geben zu können. 1136","fid":"d104e3809"}]},{"docId":"sfe-1905-004__1924","docUri":"sfe-1905-004__1924.html","score":1,"contexts":[{"form":"ausführliche","weight":"1","pos":5537,"context":"...deren Ergebnisse im einzelnen ich an 1175 anderen Orten <mark>ausführliche<\/mark> Rechenschaft gegeben habe und noch 1176 weiter geben werde....","fid":"d116e3839"}]},{"docId":"sfe-1905-004__1922","docUri":"sfe-1905-004__1922.html","score":1,"contexts":[{"form":"ausführliche","weight":"1","pos":6103,"context":"...deren Ergebnisse im einzelnen ich an 1332 anderen Orten <mark>ausführliche<\/mark> Rechenschaft gegeben habe und noch 1333 weiter geben werde...","fid":"d113e4322"}]},{"docId":"sfe-1905-004__1915","docUri":"sfe-1905-004__1915.html","score":1,"contexts":[{"form":"ausführliche","weight":"1","pos":5041,"context":"...Er- 1153gebnisse im einzelnen ich an anderen Orten <mark>ausführliche<\/mark> 1154 Rechenschaft gegeben habe und noch weiter geben werde....","fid":"d107e3807"}]},{"docId":"sfe-1905-004__1905","docUri":"sfe-1905-004__1905.html","score":1,"contexts":[{"form":"ausführliche","weight":"1","pos":5166,"context":"...über deren Ergebnisse im Einzelnen ich hoffe später 1174 <mark>ausführliche<\/mark> Rechenschaft geben zu können. 1175","fid":"d101e3777"}]},{"docId":"sfe-1905-004__1920","docUri":"sfe-1905-004__1920.html","score":1,"contexts":[{"form":"ausführliche","weight":"1","pos":6156,"context":"...deren Ergebnisse im einzelnen ich an anderen 1332 Orten <mark>ausführliche<\/mark> Rechenschaft gegeben habe und noch weiter 1333 geben werde...","fid":"d110e4439"}]},{"docId":"sfe-1901-001__1931","docUri":"sfe-1901-001__1931.html","score":1,"contexts":[{"form":"ausführlich","weight":"1","pos":639,"context":"...die sich aus seinem 142 regelmäßigen Gelingen ableiten, <mark>ausführlich<\/mark> zu behandeln. Es 143 mag also die Aussage...","fid":"d23e866"}]}]}