{"stem":"beschafft","instances":[{"docId":"sfe-1923-004__1923_1","docUri":"sfe-1923-004__1923.1.html","score":1,"contexts":[{"form":"beschafft","weight":"1","pos":1218,"context":"...droht, wenn er 231 es ihm nicht wieder <mark>beschafft<\/mark>. 232","fid":"d290e1126"}]},{"docId":"sfe-1923-004__1924","docUri":"sfe-1923-004__1924.html","score":1,"contexts":[{"form":"beschafft","weight":"1","pos":1244,"context":"...261 droht, wenn er es ihm nicht wieder <mark>beschafft<\/mark>. 262","fid":"d296e1222"}]},{"docId":"sfe-1923-004__1924_2","docUri":"sfe-1923-004__1924.2.html","score":1,"contexts":[{"form":"beschafft","weight":"1","pos":1239,"context":"...255 droht, wenn er es ihm nicht wieder <mark>beschafft<\/mark>. 256","fid":"d293e1189"}]},{"docId":"sfe-1923-004__1928","docUri":"sfe-1923-004__1928.html","score":1,"contexts":[{"form":"beschafft","weight":"1","pos":1276,"context":"...droht, wenn er es ihm nicht wieder 300 <mark>beschafft<\/mark>. 301","fid":"d299e1362"}]}]}