{"stem":"besucht","instances":[{"docId":"sfe-1900-001__1900","docUri":"sfe-1900-001__1900.html","score":7,"contexts":[{"form":"besucht","weight":"1","pos":1438,"context":"...Philosoph bei einem seiner Freunde, den er 296 <mark>besucht<\/mark>, ein kleines Album mit getrockneten Blumen, wie...","fid":"d11e1180"},{"form":"besucht","weight":"1","pos":1475,"context":"...vor 303 dem Eidechsentraum — auf der Hochzeitsreise Delboeuf <mark>besucht<\/mark>. 304 Sie hatte damals dieses für ihren Bruder...","fid":"d11e1180"},{"form":"besuchte","weight":"1","pos":16303,"context":"...Sommerzeit wegen 3179 die Behandlung ab. — Eines Tages <mark>besuchte<\/mark> mich ein jüngerer 3180 College, einer meiner nächsten...","fid":"d11e9642"},{"form":"besucht","weight":"1","pos":16314,"context":"...Irma — 3181 und ihre Familie in ihrem Landaufenthalt <mark>besucht<\/mark> hatte. Ich fragte 3182 ihn, wie er sie gefunden...","fid":"d11e9642"},{"form":"besuchte","weight":"1","pos":21042,"context":"Eines Abends <mark>besuchte<\/mark> mich ein befreundeter College, einer von 4159 denjenigen...","fid":"d11e12234"},{"form":"besucht","weight":"1","pos":29843,"context":"...Träumer hatte mit zwölf Jahren einen bettlägerigen 5991 Collagen <mark>besucht<\/mark>, der sich wahrscheinlich nur zufällig bei einer 5992...","fid":"d11e17277"},{"form":"besuchte","weight":"1","pos":55656,"context":"...er leugnete, und als ich ihn als Todtkranken <mark>besuchte<\/mark> und nach[\/] 11272252seinem Befinden fragte, verweilte er...","fid":"d11e32470"}]},{"docId":"sfe-1922-001__1922_2","docUri":"sfe-1922-001__1922.2.html","score":1,"contexts":[{"form":"besuchte","weight":"1","pos":2361,"context":"Von sechs bis zehn Jahren <mark>besuchte<\/mark> ich die Gemeindeschule und dann 489 bis sechzehn Jahre...","fid":"d248e1522"}]}]}