{"stem":"brauchen","instances":[{"docId":"sfe-1900-001__1900","docUri":"sfe-1900-001__1900.html","score":7,"contexts":[{"form":"brauchen","weight":"1","pos":5258,"context":"..., 1046 dass die Organe nicht erst zu erkranken <mark>brauchen<\/mark>, um Erregungen, 1047 die irgendwie zu Traumbildern...","fid":"d11e3379"},{"form":"brauchen","weight":"1","pos":33303,"context":"...nur an die Ergebnisse dieser Untersuchungen er- 6706innern <mark>brauchen<\/mark>. Wir haben gehört, dass dreierlei somatische Reiz...","fid":"d11e19643"},{"form":"brauchen","weight":"1","pos":54531,"context":"...vermittelt die 11032 Redensart: Wir werden keinen Richter <mark>brauchen<\/mark>.) Dass er auf 11033 dem nodtenbette Garibaldi so...","fid":"d11e31768"},{"form":"brauchen","weight":"1","pos":68817,"context":"...Deutungsarbeit auch 13976 in die nächtliche Traumarbeit zu versetzen <mark>brauchen<\/mark>. Wir machen 13977 ja beim Deuten im Wachen...","fid":"d11e39801"},{"form":"brauchen","weight":"1","pos":69544,"context":"...des Fernrohres hinter einander stehen. Streng genommen 14130 <mark>brauchen<\/mark> wir die Annahme einer wirklich räumlichen Anordnung 14131 der...","fid":"d11e40178"},{"form":"brauchen","weight":"1","pos":71030,"context":"...besonderen Reichthum an solchen erkennen 14437 lassen. Wir <mark>brauchen<\/mark> uns gegen diese Annahme nicht zu sträuben, 14438...","fid":"d11e41038"},{"form":"brauchen","weight":"1","pos":79184,"context":"...Verdrängung, 16089 das wir hier nur zu streifen <mark>brauchen<\/mark>. Es genügt uns festzuhalten, 16090 dass eine...","fid":"d11e45398"}]},{"docId":"sfe-1923-005__1923","docUri":"sfe-1923-005__1923.html","score":2,"contexts":[{"form":"brauchen","weight":"1","pos":2299,"context":"...für welche die Psychoanalyse das unpassende Wort unbewußt ge- <mark>brauchen<\/mark> wolle. Sie seien aber doch auch bewußt oder...","fid":"page"},{"form":"brauchen","weight":"1","pos":6472,"context":"...- 1578digung d. i. Abfuhrmöglichkeit bietet. Somit <mark>brauchen<\/mark> 1579 wir für keinen dieser Fälle eine direkte Verwandlung...","fid":"d302e4789"}]},{"docId":"sfe-1905-001__1906","docUri":"sfe-1905-001__1906.html","score":1,"contexts":[{"form":"brauchen","weight":"1","pos":1720,"context":"...ist durch das Unbewußte be- 388gründet. Sie <mark>brauchen<\/mark> auch niemals zu fürchten, daß der 389 Kranke...","fid":"d77e1619"}]},{"docId":"sfe-1905-001__1920","docUri":"sfe-1905-001__1920.html","score":1,"contexts":[{"form":"brauchen","weight":"1","pos":1694,"context":"...Zwang ist durch das Unbewußte begründet. 372 Sie <mark>brauchen<\/mark> auch niemals zu fürchten, daß der Kranke unter...","fid":"d83e1585"}]},{"docId":"sfe-1920-006__1931","docUri":"sfe-1920-006__1931.html","score":1,"contexts":[{"form":"brauchen","weight":"1","pos":7527,"context":"...für Objektbesetzungen ver-[\/] 1698231ausgabt. Die Keimzellen <mark>brauchen<\/mark> ihre Libido, die Tätigkeit 1699 ihrer Lebenstriebe,...","fid":"d224e4943"}]},{"docId":"sfe-1905-001__1925","docUri":"sfe-1905-001__1925.html","score":1,"contexts":[{"form":"brauchen","weight":"1","pos":1705,"context":"...Zwang 370 ist durch das Unbewußte begründet. Sie <mark>brauchen<\/mark> auch niemals 371 zu fürchten, daß der Kranke...","fid":"d92e1644"}]},{"docId":"sfe-1905-001","docUri":"sfe-1905-001.html","score":1,"contexts":[{"form":"brauchen","weight":"1","pos":1675,"context":"...Zwang 340 ist durch das Unbewußte begründet. Sie <mark>brauchen<\/mark> auch niemals 341 zu fürchten, daß der Kranke...","fid":"d15e1879"}]},{"docId":"sfe-1920-006__1925","docUri":"sfe-1920-006__1925.html","score":1,"contexts":[{"form":"brauchen","weight":"1","pos":7441,"context":"...von ihr für Objektbesetzungen verausgabt. Die Keimzellen 1596 <mark>brauchen<\/mark> ihre Libido, die Tätigkeit ihrer Lebenstriebe, für...","fid":"d221e4707"}]},{"docId":"sfe-1905-001__1911","docUri":"sfe-1905-001__1911.html","score":1,"contexts":[{"form":"brauchen","weight":"1","pos":1693,"context":"...Zwang ist durch das Unbewußte begründet. 372 Sie <mark>brauchen<\/mark> auch niemals zu fürchten, daß der Kranke unter...","fid":"d80e1580"}]},{"docId":"sfe-1905-004__1905","docUri":"sfe-1905-004__1905.html","score":1,"contexts":[{"form":"brauchen","weight":"1","pos":9578,"context":"...„sexuelle Erregung“ und „Befriedigung“ unterschiedslos ge- 2115<mark>brauchen<\/mark> dürfen, und legt uns die Pflicht auf, später nach...","fid":"d107e6282"}]},{"docId":"sfe-1905-002__1937","docUri":"sfe-1905-002__1937.html","score":1,"contexts":[{"form":"brauchen","weight":"1","pos":1483,"context":"Auch die religiös Ungläubigen <mark>brauchen<\/mark> auf Wunderheilungen nicht zu 275 verzichten. Das Ansehen...","fid":"d104e1204"}]},{"docId":"sfe-1920-006__1920_1","docUri":"sfe-1920-006__1920.1.html","score":1,"contexts":[{"form":"brauchen","weight":"1","pos":8507,"context":"...Objektbesetz- 1970ungen verausgabt. Die Keimzellen 1971 <mark>brauchen<\/mark> ihre Libido, die Tätigkeit ihrer 1972 Lebenstriebe für...","fid":"d209e7090"}]},{"docId":"sfe-1905-001__1922","docUri":"sfe-1905-001__1922.html","score":1,"contexts":[{"form":"brauchen","weight":"1","pos":1693,"context":"...Zwang ist durch das Unbewußte begründet. 372 Sie <mark>brauchen<\/mark> auch niemals zu fürchten, daß der Kranke unter...","fid":"d86e1586"}]},{"docId":"sfe-1905-002__1905","docUri":"sfe-1905-002__1905.html","score":1,"contexts":[{"form":"brauchen","weight":"1","pos":1452,"context":"Auch die religiös Ungläubigen <mark>brauchen<\/mark> auf Wunderheilungen nicht 278 zu verzichten. Das Ansehen...","fid":"d98e1185"}]},{"docId":"sfe-1905-001__1905_2","docUri":"sfe-1905-001__1905.2.html","score":1,"contexts":[{"form":"brauchen","weight":"1","pos":1807,"context":"...420 Zwang ist durch das Unbewußte begründet. Sie <mark>brauchen<\/mark> 421 auch niemals zu fürchten, daß der Kranke...","fid":"d71e1726"}]},{"docId":"sfe-1905-002__1918","docUri":"sfe-1905-002__1918.html","score":1,"contexts":[{"form":"brauchen","weight":"1","pos":1452,"context":"Auch die religiös Ungläubigen <mark>brauchen<\/mark> auf Wunderheilungen nicht 278 zu verzichten. Das Ansehen...","fid":"d101e1185"}]},{"docId":"sfe-1923-005__1925","docUri":"sfe-1923-005__1925.html","score":1,"contexts":[{"form":"brauchen","weight":"1","pos":4764,"context":"..., 1062 das ist Abfuhrmöglichkeit, bietet. Somit <mark>brauchen<\/mark> wir für keinen 1063 dieser Fälle eine direkte Verwandlung...","fid":"d305e3416"}]},{"docId":"sfe-1905-001__1905","docUri":"sfe-1905-001__1905.html","score":1,"contexts":[{"form":"brauchen","weight":"1","pos":1755,"context":"...396 Zwang ist durch das Unbewußte begründet. Sie <mark>brauchen<\/mark> 397 auch niemals zu fürchten, daß der Kranke...","fid":"d74e1605"}]},{"docId":"sfe-1905-002__1905_2","docUri":"sfe-1905-002__1905.2.html","score":1,"contexts":[{"form":"brauchen","weight":"1","pos":1467,"context":"Auch die religiös Ungläubigen <mark>brauchen<\/mark> auf Wunderheilungen nicht 282 zu verzichten. Das Ansehen...","fid":"d95e1209"}]},{"docId":"sfe-1920-006__1920_2","docUri":"sfe-1920-006__1920.2.html","score":1,"contexts":[{"form":"brauchen","weight":"1","pos":7678,"context":"...von ihr für Objektbesetzungen verausgabt. Die 1601 Keimzellen <mark>brauchen<\/mark> ihre Libido, die Tätigkeit ihrer Lebenstriebe, 1602...","fid":"d212e4728"}]},{"docId":"sfe-1922-001__1922_2","docUri":"sfe-1922-001__1922.2.html","score":1,"contexts":[{"form":"brauchen","weight":"1","pos":2385,"context":"...Überhaupt habe ich auch später Französisch nie zu lernen <mark>brauchen<\/mark>, im Gegen- 494satz zu Englisch, das...","fid":"d248e1522"}]},{"docId":"sfe-1920-006__1921","docUri":"sfe-1920-006__1921.html","score":1,"contexts":[{"form":"brauchen","weight":"1","pos":7595,"context":"...von ihr für Objektbesetzungen 1667 verausgabt. Die Keimzellen <mark>brauchen<\/mark> ihre Libido, die Tätigkeit 1668 ihrer Lebenstriebe,...","fid":"d215e4820"}]},{"docId":"sfe-1905-001__1924","docUri":"sfe-1905-001__1924.html","score":1,"contexts":[{"form":"brauchen","weight":"1","pos":1705,"context":"...Zwang 370 ist durch das Unbewußte begründet. Sie <mark>brauchen<\/mark> auch niemals 371 zu fürchten, daß der Kranke...","fid":"d89e1599"}]},{"docId":"sfe-1905-004__1910","docUri":"sfe-1905-004__1910.html","score":1,"contexts":[{"form":"brauchen","weight":"1","pos":9934,"context":"...„sexuelle Erregung“ und „Befriedigung“ unterschiedslos ge- 2189<mark>brauchen<\/mark> dürfen, und legt uns die Pflicht auf, später nach...","fid":"d110e6724"}]},{"docId":"sfe-1920-006__1923","docUri":"sfe-1920-006__1923.html","score":1,"contexts":[{"form":"brauchen","weight":"1","pos":7617,"context":"...von ihr für Objektbesetzungen verausgabt. 1863 Die Keimzellen <mark>brauchen<\/mark> ihre Libido, die Tätigkeit 1864 ihrer Lebenstriebe,...","fid":"d218e5332"}]}]}