{"stem":"famili","instances":[{"docId":"sfe-1901-001__1931","docUri":"sfe-1901-001__1931.html","score":2,"contexts":[{"form":"Familie","weight":"1","pos":3973,"context":"...größere Geldausgabe 896 für eine mir teuere Person meiner <mark>Familie<\/mark> gemacht. Kein 897 Wunder, heißt es in den...","fid":"d23e3007"},{"form":"Familie","weight":"1","pos":6442,"context":"...die letzten kostspieligen Wagenfahrten mit einer 1468 Person meiner <mark>Familie<\/mark> gemahnt hat, daß sich als die Deutung 1469 des...","fid":"d23e4754"}]},{"docId":"sfe-1901-001__1921","docUri":"sfe-1901-001__1921.html","score":2,"contexts":[{"form":"Familie","weight":"1","pos":3881,"context":"...grössere Geldausgabe für eine mir 802 teuere Person meiner <mark>Familie<\/mark> gemacht. Kein Wunder, heisst es in den 803...","fid":"d17e2642"},{"form":"Familie","weight":"1","pos":6274,"context":"...kostspieligen Wagen- 1303fahrten mit einer Person meiner <mark>Familie<\/mark> gemahnt hat, dass sich als die 1304 Deutung des...","fid":"d17e4198"}]},{"docId":"sfe-1901-001","docUri":"sfe-1901-001.html","score":2,"contexts":[{"form":"Familie","weight":"1","pos":4011,"context":"...Geldausgabe für eine mir teuereqd Person meiner 853 <mark>Familie<\/mark> gemacht. Kein Wunder, heißtqe es in den...","fid":"d11e6707"},{"form":"Familie","weight":"1","pos":6411,"context":"...1359 letzten kostspieligen Wagenfahrten mit einer Person meiner 1360 <mark>Familie<\/mark> gemahnt hat, daßaaj sich als die Deutung des...","fid":"d11e10748"}]},{"docId":"sfe-1901-001__1925","docUri":"sfe-1901-001__1925.html","score":2,"contexts":[{"form":"Familie","weight":"1","pos":3997,"context":"...größere Geldausgabe für eine mir teuere Person meiner 867 <mark>Familie<\/mark> gemacht. Kein Wunder, heißt es in den Traumgedanken...","fid":"d20e3000"},{"form":"Familie","weight":"1","pos":6400,"context":"...1397 letzten kostspieligen Wagenfahrten mit einer Person meiner 1398 <mark>Familie<\/mark> gemahnt hat, daß sich als die Deutung des Traumes...","fid":"d20e4648"}]},{"docId":"sfe-1901-001__1911","docUri":"sfe-1901-001__1911.html","score":2,"contexts":[{"form":"Familie","weight":"1","pos":3877,"context":"...grössere Geldausgabe für eine mir teuere 801 Person meiner <mark>Familie<\/mark> gemacht. Kein Wunder, heißt es in den Traum...","fid":"d14e2636"},{"form":"Familie","weight":"1","pos":6252,"context":"...die letzten kostspieligen 1294 Wagenfahrten mit einer Person meiner <mark>Familie<\/mark> gemahnt hat, dass sich 1295 als die Deutung des...","fid":"d14e4168"}]},{"docId":"sfe-1901-001__1901","docUri":"sfe-1901-001__1901.html","score":2,"contexts":[{"form":"Familie","weight":"1","pos":3933,"context":"...grössere Geldausgabe für eine mir theuere 822 Person meiner <mark>Familie<\/mark> gemacht. Kein Wunder, heisst es in den Traum...","fid":"d11e2698"},{"form":"Familie","weight":"1","pos":6242,"context":"...die letzten kostspieligen 1300 Wagenfahrten mit einer Person meiner <mark>Familie<\/mark> gemahnt hat, dass sich 1301 als die Deutung des...","fid":"d11e4165"}]},{"docId":"sfe-1905-009__1909","docUri":"sfe-1905-009__1909.html","score":1,"contexts":[{"form":"Familie","weight":"1","pos":97,"context":"Biographien nebst Bibliographien. Angaben über Herkunft, <mark>Familie<\/mark>, Lebenslauf, Werke, Lieblingsbeschäftigungen, Partei angehörigkeit...","fid":"d122e772"}]},{"docId":"sfe-1905-009__1905","docUri":"sfe-1905-009__1905.html","score":1,"contexts":[{"form":"Familie","weight":"1","pos":15,"context":"...Biographien nebst Bibliographien. Angaben 005 über Herkunft, <mark>Familie<\/mark>, Lebenslauf, Werke, 006 Lieblingsbeschäftigungen, Parteiangehörigkeit...","fid":"d113e681"}]},{"docId":"sfe-1905-009__1912","docUri":"sfe-1905-009__1912.html","score":1,"contexts":[{"form":"Familie","weight":"1","pos":117,"context":"<mark>Familie<\/mark>, Lebenslauf,Werke, Ueblingsbeschlitigungen, Partei-...","fid":"d128e772"}]},{"docId":"sfe-1905-009__1906","docUri":"sfe-1905-009__1906.html","score":1,"contexts":[{"form":"Familie","weight":"1","pos":88,"context":"...Biographien nebst Bibliographien. Angaben 021 über Herkunft, <mark>Familie<\/mark>, Lebenslauf, Werke, 022 Lieblingsbeschäftigungen, Parteiangehörigkeit...","fid":"d116e759"}]}]}