{"stem":"fürsorg","instances":[{"docId":"sfe-1905-004__1925","docUri":"sfe-1905-004__1925.html","score":2,"contexts":[{"form":"Fürsorge","weight":"1","pos":11872,"context":"...vor 2447 dem mit diesem Ereignis verbundenen Verlust an <mark>Fürsorge<\/mark> 2448 und Liebe machen das Kind nachdenklich und scharfsinnig...","fid":"d119e7576"},{"form":"Fürsorge","weight":"1","pos":17814,"context":"...Verwendung männlicher Dienerschaft 3703 wie durch die geringere persönliche <mark>Fürsorge<\/mark> der Mütter für 3704 ihre Kinder um etwas verständlicher...","fid":"d119e10876"}]},{"docId":"sfe-1905-004__1924","docUri":"sfe-1905-004__1924.html","score":2,"contexts":[{"form":"Fürsorge","weight":"1","pos":10844,"context":"...vor 2284 dem mit diesem Ereignis verbundenen Verlust an <mark>Fürsorge<\/mark> 2285 und Liebe machen das Kind nachdenklich und scharfsinnig...","fid":"d116e6938"},{"form":"Fürsorge","weight":"1","pos":16786,"context":"...Verwendung männlicher Dienerschaft 3540 wie durch die geringere persönliche <mark>Fürsorge<\/mark> der Mütter für 3541 ihre Kinder um etwas verständlicher...","fid":"d116e10235"}]},{"docId":"sfe-1905-004__1922","docUri":"sfe-1905-004__1922.html","score":2,"contexts":[{"form":"Fürsorge","weight":"1","pos":11443,"context":"...vor 2478 dem mit diesem Ereignis verbundenen Verlust an <mark>Fürsorge<\/mark> 2479 und Liebe machen das Kind nachdenklich und scharfsinnig...","fid":"d113e7533"},{"form":"Fürsorge","weight":"1","pos":17156,"context":"...- 3712licher Dienerschaft wie durch die geringere persönliche <mark>Fürsorge<\/mark> 3713 der Mütter für ihre Kinder um etwas verständlicher...","fid":"d113e10703"}]},{"docId":"sfe-1905-004__1915","docUri":"sfe-1905-004__1915.html","score":2,"contexts":[{"form":"Fürsorge","weight":"1","pos":10176,"context":"...mit diesem Ereignis verbundenen Ver- 2272lust an <mark>Fürsorge<\/mark> und Liebe machen das Kind nachdenklich 2273 und scharfsinnig...","fid":"d107e6896"},{"form":"Fürsorge","weight":"1","pos":15780,"context":"...Verwendung männlicher Dienerschaft wie durch 3510 die geringere persönliche <mark>Fürsorge<\/mark> der Mütter für ihre Kinder 3511 um etwas verständlicher...","fid":"d107e10078"}]},{"docId":"sfe-1905-004__1920","docUri":"sfe-1905-004__1920.html","score":2,"contexts":[{"form":"Fürsorge","weight":"1","pos":11484,"context":"...vor dem mit diesem Ereignis verbundenen Verlust an 2478 <mark>Fürsorge<\/mark> und Liebe machen das Kind nachdenklich und 2479 scharfsinnig...","fid":"d110e7759"},{"form":"Fürsorge","weight":"1","pos":17191,"context":"...- 3713licher Dienerschaft wie durch die geringere persönliche <mark>Fürsorge<\/mark> 3714 der Mütter für ihre Kinder um etwas verständlicher...","fid":"d110e11004"}]},{"docId":"sfe-1905-004__1910","docUri":"sfe-1905-004__1910.html","score":1,"contexts":[{"form":"Fürsorge","weight":"1","pos":13869,"context":"...Diener- 3037schaft wie durch die geringere persönliche <mark>Fürsorge<\/mark> der Mütter 3038 für ihre Kinder um etwas verständlicher...","fid":"d104e8814"}]},{"docId":"sfe-1905-004__1905","docUri":"sfe-1905-004__1905.html","score":1,"contexts":[{"form":"Fürsorge","weight":"1","pos":13377,"context":"...Diener- 2935schaft wie durch die geringere persönliche <mark>Fürsorge<\/mark> der Mütter 2936 für ihre Kinder um etwas verständlicher...","fid":"d101e8281"}]}]}