{"stem":"gelegenheit","instances":[{"docId":"sfe-1901-001","docUri":"sfe-1901-001.html","score":2,"contexts":[{"form":"Gelegenheit","weight":"1","pos":1107,"context":"...seinem Schuldner gemacht. Ich habe erst unl채ngst 221 eine <mark>Gelegenheit<\/mark>, es ihm zu vergelten, ungen체tzt vor체bergehen 222...","fid":"d11e1993"},{"form":"Gelegenheit","weight":"1","pos":6966,"context":"...Situation auf die f체r eine freudige Empfindung 1465 unpassendste <mark>Gelegenheit<\/mark> verschoben worden, die sich doch ein- 1466 mal in...","fid":"d11e11497"}]}]}