{"stem":"gleichzustellenden","instances":[{"docId":"sfe-1923-004__1924","docUri":"sfe-1923-004__1924.html","score":1,"contexts":[{"form":"gleichzustellenden","weight":"1","pos":4601,"context":"...die späteren in einem besonderen, seinen 978 Visionen <mark>gleichzustellenden<\/mark> Zustand geschrieben und mit sich ge- 979nommen hat....","fid":"d296e3180"}]},{"docId":"sfe-1923-004__1924_2","docUri":"sfe-1923-004__1924.2.html","score":1,"contexts":[{"form":"gleichzustellenden","weight":"1","pos":4595,"context":"...die späteren in einem besonderen, seinen 968 Visionen <mark>gleichzustellenden<\/mark> Zustand geschrieben und mit sich ge- 969nommen hat....","fid":"d293e3114"}]},{"docId":"sfe-1923-004__1928","docUri":"sfe-1923-004__1928.html","score":1,"contexts":[{"form":"gleichzustellenden","weight":"1","pos":4621,"context":"...späteren in einem besonderen, seinen Vi- 1084sionen <mark>gleichzustellenden<\/mark> Zustand geschrieben und mit 1085 sich genommen hat. Wenn...","fid":"d299e3484"}]}]}