{"stem":"kindesjahren","instances":[{"docId":"sfe-1900-001__1900","docUri":"sfe-1900-001__1900.html","score":2,"contexts":[{"form":"Kindesjahren","weight":"1","pos":39879,"context":"...bewusst 8015 ge채ussert hatten, aber nat체rlich aus weit fr체heren <mark>Kindesjahren<\/mark> 8016 stammten. Nach der qualvollen Krankheit und dem...","fid":"d11e23001"},{"form":"Kindesjahren","weight":"1","pos":40392,"context":"...und unseren Stolz, die wir seit 8116 den <mark>Kindesjahren<\/mark> so weise und so m채chtig geworden sind in unserer...","fid":"d11e23232"}]}]}