{"stem":"leitet","instances":[{"docId":"sfe-1901-001","docUri":"sfe-1901-001.html","score":2,"contexts":[{"form":"leitet","weight":"1","pos":2784,"context":"...Die Situation 584 in dem zur Analyse gewählten Beispiel <mark>leitet<\/mark> mich bei der Ana- 585 lyse auf eine...","fid":"d11e4646"},{"form":"leitet","weight":"1","pos":3854,"context":"...817 Ein gutes Stück der Mißachtungpj des Traumes <mark>leitet<\/mark> sich von 818 dieser Bevorzugung des Gleichgültigenpk und...","fid":"d11e6381"}]}]}