{"stem":"our","instances":[{"docId":"sfe-1921-002__1928","docUri":"sfe-1921-002__1928.html","score":2,"contexts":[{"form":"our","weight":"1","pos":517,"context":"It is <mark>our<\/mark> duty to express our thanks to the author’s widow...","fid":"d236e502"},{"form":"our","weight":"1","pos":520,"context":"It is our duty to express <mark>our<\/mark> thanks to the author’s widow, Mrs. Pumami...","fid":"d236e502"}]},{"docId":"sfe-1900-001__1900","docUri":"sfe-1900-001__1900.html","score":2,"contexts":[{"form":"our","weight":"1","pos":2441,"context":"..., the questions and problems on which we spread <mark>our<\/mark> chief volun- 497tary mental energy, are...","fid":"d11e1785"},{"form":"our","weight":"1","pos":2479,"context":"...- 500sions of daily life which reappear in <mark>our<\/mark> dreams. The psychic aeti- 501vities that...","fid":"d11e1785"}]},{"docId":"sfe-1921-002__1921","docUri":"sfe-1921-002__1921.html","score":2,"contexts":[{"form":"our","weight":"1","pos":551,"context":"It is <mark>our<\/mark> duty to express our thanks to the author’s 079...","fid":"d233e576"},{"form":"our","weight":"1","pos":554,"context":"It is our duty to express <mark>our<\/mark> thanks to the author’s 079 widow, Mrs....","fid":"d233e576"}]},{"docId":"sfe-1922-002__1922","docUri":"sfe-1922-002__1922.html","score":1,"contexts":[{"form":"our","weight":"1","pos":2115,"context":"...Dr. J-A. Jackson and H.M. Salisbury: Outwitting <mark>our<\/mark> Nerves (E. J.) 444 T. W. Mitchell: The...","fid":"d254e1512"}]}]}