{"stem":"psycho-analysi","instances":[{"docId":"sfe-1920-002__1920_2","docUri":"sfe-1920-002__1920.2.html","score":1,"contexts":[{"form":"Psycho-Analysis","weight":"1","pos":30,"context":"...004 London 1919, ist ein Aufsatz: „<mark>Psycho-Analysis<\/mark> in relation to sex“ ent- 005halten,...","fid":"d155e521"}]},{"docId":"sfe-1920-002__1924_2","docUri":"sfe-1920-002__1924.2.html","score":1,"contexts":[{"form":"Psycho-Analysis","weight":"1","pos":50,"context":"...London 1919, ist ein Aufsatz: 010 „<mark>Psycho-Analysis<\/mark> in relation to sex“ enthalten, der sich nach-...","fid":"d164e544"}]},{"docId":"sfe-1920-002__1924","docUri":"sfe-1920-002__1924.html","score":1,"contexts":[{"form":"Psycho-Analysis","weight":"1","pos":50,"context":"...London 1919, ist ein Aufsatz: 010 „<mark>Psycho-Analysis<\/mark> in relation to sex“ enthalten, der sich nach-...","fid":"d167e541"}]},{"docId":"sfe-1920-002__1920","docUri":"sfe-1920-002__1920.html","score":1,"contexts":[{"form":"Psycho-Analysis","weight":"1","pos":29,"context":"...003 London 1919, ist ein Aufsatz: „<mark>Psycho-Analysis<\/mark> in relation to sex“ ent- 004halten,...","fid":"d158e529"}]},{"docId":"sfe-1920-002__1922","docUri":"sfe-1920-002__1922.html","score":1,"contexts":[{"form":"Psycho-Analysis","weight":"1","pos":34,"context":"...London 1919, ist ein Aufsatz: 006 „<mark>Psycho-Analysis<\/mark> in relation to sex“ enthalten, der sich nach-...","fid":"d161e532"}]},{"docId":"sfe-1923-009__1923_1","docUri":"sfe-1923-009__1923.1.html","score":1,"contexts":[{"form":"Psycho-Analysis","weight":"1","pos":294,"context":"...ins Englische übersetzt 055 worden ist (Contributions to <mark>Psycho-Analysis<\/mark> 1916), steht noch 056 aus. Der Verlag wird...","fid":"d212e588"}]},{"docId":"sfe-1923-009__1928","docUri":"sfe-1923-009__1928.html","score":1,"contexts":[{"form":"Psycho-Analysis","weight":"1","pos":308,"context":"...ins Englische übersetzt worden ist 053 (Contributions to <mark>Psycho-Analysis<\/mark> 1916), steht noch aus. Der Verlag wird 054...","fid":"d215e582"}]}]}