{"stem":"untergekommen","instances":[{"docId":"sfe-1923-003__1925","docUri":"sfe-1923-003__1925.html","score":1,"contexts":[{"form":"untergekommen","weight":"1","pos":32,"context":"...die sonst als 006 Abänderungen oder Einschaltungen im Text <mark>untergekommen<\/mark> 007 wären. 008","fid":"d284e482"}]},{"docId":"sfe-1900-001__1900","docUri":"sfe-1900-001__1900.html","score":1,"contexts":[{"form":"untergekommen","weight":"1","pos":34665,"context":"...die andere nur den früheren 6964 Beurtheilern des Traumes <mark>untergekommen<\/mark> ist. Es erübrigt nur noch, 6965 den Thatsachen,...","fid":"d11e20348"}]},{"docId":"sfe-1923-003__1923_1","docUri":"sfe-1923-003__1923.1.html","score":1,"contexts":[{"form":"untergekommen","weight":"1","pos":26,"context":"...die sonst als 004 Abänderungen oder Einschaltungen im Text <mark>untergekommen<\/mark> 005 wären. 006","fid":"d281e484"}]},{"docId":"sfe-1923-003__1931","docUri":"sfe-1923-003__1931.html","score":1,"contexts":[{"form":"untergekommen","weight":"1","pos":28,"context":"...die sonst als Abänderungen oder Einschaltungen im Text 006 <mark>untergekommen<\/mark> wären. 007","fid":"d287e482"}]}]}